postmark_template_translate/__init__.py
postmark_template_translate/postmark/__init__.py
postmark_template_translate/postmark/config.py
postmark_template_translate/translate/__init__.py
postmark_template_translate/translate/translate.py
postmark_template_translate-0.7.1.dist-info/METADATA
postmark_template_translate-0.7.1.dist-info/WHEEL
postmark_template_translate-0.7.1.dist-info/top_level.txt
postmark_template_translate-0.7.1.dist-info/RECORD
